scripts/control_gridworld_q_learner.py
scripts/gridworld_policy_eval.py
scripts/gridworld_q_learner.py
scripts/roulette_learner.py
table_rl/__init__.py
table_rl/explorer.py
table_rl/learner.py
table_rl/step_size_scheduler.py
table_rl/dp/__init__.py
table_rl/dp/dp.py
table_rl/envs/__init__.py
table_rl/envs/basic_gridworld.py
table_rl/envs/control_gridworld.py
table_rl/envs/overestimation_env.py
table_rl/envs/river_swim.py
table_rl/envs/roulette.py
table_rl/envs/test_env.py
table_rl/explorers/__init__.py
table_rl/explorers/epsilon_greedy.py
table_rl/explorers/greedy.py
table_rl/explorers/policy_executor.py
table_rl/explorers/random_explorer.py
table_rl/learners/__init__.py
table_rl/learners/double_q_learning.py
table_rl/learners/expected_sarsa.py
table_rl/learners/q_learning.py
table_rl/learners/qv.py
table_rl/learners/sarsa.py
table_rl/step_size_schedulers/__init__.py
table_rl/step_size_schedulers/basic_step_size_schedulers.py
table_rl/utils/__init__.py
table_rl/utils/sr_learner.py
table_rl-0.3.0.dist-info/licenses/LICENSE
tests/test_dp.py
tests/env_tests/overestimation_env_test.py
tests/explorers_tests/test_epsilon_greedy.py
tests/explorers_tests/test_explorers.py
tests/learner_tests/test_double_q_learning.py
tests/learner_tests/test_dueling_q_learning.py
tests/learner_tests/test_expected_sarsa.py
tests/learner_tests/test_q_learning.py
tests/learner_tests/test_qv_learning.py
tests/learner_tests/test_sarsa.py
table_rl-0.3.0.dist-info/METADATA
table_rl-0.3.0.dist-info/WHEEL
table_rl-0.3.0.dist-info/top_level.txt
table_rl-0.3.0.dist-info/RECORD
