Metadata-Version: 2.4
Name: table-rl
Version: 0.3.0
Summary: table-rl, an online tabular reinforcement learning library
Author-email: Prabhat Nagarajan <nagarajan@ualberta.ca>
License: MIT License
Classifier: Programming Language :: Python :: 3
Classifier: License :: OSI Approved :: MIT License
Classifier: Operating System :: OS Independent
Requires-Python: >=3.8
License-File: LICENSE
Requires-Dist: gymnasium
Requires-Dist: numpy>=1.10.4
Provides-Extra: test
Requires-Dist: pytest; extra == "test"
Requires-Dist: attrs<19.2.0; extra == "test"
Dynamic: license-file
